{
  
  "video_processor": {
    "record": "False",
    "record_time": "00:00-00:01",
    "record_weekday": 3,
    "gamma_filter": 1.0,
    "interactive": "False",
    "show_input_bbox": "False",
    "show_tracking_bbox": "False",
    "show_id": "True",
    "num_frame_output": 22500,
    "lines_dimensions": [416, 416]
  },
  
  "video_analyser": {
    "comment": "When identification of objects is easy, then augmenting the 'skip_detection_frames' is good as we reduce the number of matches between new objects and tracked object.  It also is more efficient.",
    "comment": "Run detection every 20 frames.",
    "skip_detection_frames": 20,
    "track_every_x_frames": 1
  },
  
  "trackable_objects": {
    "algorithm": "dlib",
    "match": "iou_match",
    "iou_match": 0.3,
    "centroid_match_max_distance": 2000,
    "drop_overlap": 0.5,
    "disappear": 50
  },
  
  "counting_lines": {
  },
  
  "entry_lines": {
  }
  
}
